toasts_winrt/_winrt.pyd
toasts_winrt/_winrt.pyi
toasts_winrt/py.typed
toasts_winrt/system/__init__.py
toasts_winrt/windows/data/xml/dom/__init__.py
toasts_winrt/windows/data/xml/dom/__init__.pyi
toasts_winrt/windows/foundation/__init__.py
toasts_winrt/windows/foundation/__init__.pyi
toasts_winrt/windows/foundation/collections/__init__.py
toasts_winrt/windows/foundation/collections/__init__.pyi
toasts_winrt/windows/ui/notifications/__init__.py
toasts_winrt/windows/ui/notifications/__init__.pyi
toasts_winrt/windows/ui/notifications/management/__init__.py
toasts_winrt/windows/ui/notifications/management/__init__.pyi
toasts_winrt-1.0.0.dist-info/LICENSE
toasts_winrt-1.0.0.dist-info/METADATA
toasts_winrt-1.0.0.dist-info/WHEEL
toasts_winrt-1.0.0.dist-info/top_level.txt
toasts_winrt-1.0.0.dist-info/RECORD
