Metadata-Version: 2.1
Name: toasts-winrt
Version: 1.0.0
Summary: Python WinRT bindings for Windows-Toasts
Home-page: https://github.com/DatGuy1/toasts-winrt
Author: DatGuy
License: MIT
Classifier: Development Status :: 4 - Beta
Classifier: Environment :: Win32 (MS Windows)
Classifier: License :: OSI Approved :: MIT License
Classifier: Operating System :: Microsoft :: Windows :: Windows 10
Classifier: Programming Language :: Python :: 3.8
Classifier: Programming Language :: Python :: 3.9
Classifier: Programming Language :: Python :: 3.10
Classifier: Programming Language :: Python :: 3.11
Classifier: Programming Language :: Python :: 3.12
Classifier: Programming Language :: Python :: Implementation :: CPython
Classifier: Topic :: System :: Operating System
Requires-Python: >=3.8
License-File: LICENSE
